dmenutrello/__init__.py
dmenutrello/dmenutrello.py
dmenutrello-0.1.6.dist-info/LICENSE
dmenutrello-0.1.6.dist-info/METADATA
dmenutrello-0.1.6.dist-info/WHEEL
dmenutrello-0.1.6.dist-info/entry_points.txt
dmenutrello-0.1.6.dist-info/top_level.txt
dmenutrello-0.1.6.dist-info/RECORD
