Metadata-Version: 2.1
Name: dmenutrello
Version: 0.1.6
Summary: brings trello to dmenu
Home-page: https://github.com/ljurk/dmenutrello
Author: Lukas Jurk
Author-email: ljurk@pm.me
License: GPLv3
Keywords: trello dmenu
Platform: UNKNOWN
Classifier: Programming Language :: Python :: 2
Classifier: Programming Language :: Python :: 3
Requires-Dist: dmenu
Requires-Dist: configparser
Requires-Dist: py-trello
